{
    "collision_meshes": [
        {
            "dtype": "compas.datastructures/Mesh", 
            "guid": "692476ff-8a46-4bfc-93eb-8d470c1b7c97", 
            "value": {
                "attributes": {
                    "name": null
                }, 
                "dea": {}, 
                "dfa": {}, 
                "dva": {
                    "x": 0.0, 
                    "y": 0.0, 
                    "z": 0.0
                }, 
                "edgedata": {}, 
                "face": {
                    "0": [
                        1, 
                        0, 
                        2
                    ], 
                    "1": [
                        5, 
                        4, 
                        6
                    ], 
                    "2": [
                        9, 
                        8, 
                        10
                    ], 
                    "3": [
                        13, 
                        12, 
                        14
                    ], 
                    "4": [
                        17, 
                        19, 
                        18
                    ], 
                    "5": [
                        21, 
                        20, 
                        22
                    ], 
                    "6": [
                        1, 
                        2, 
                        3
                    ], 
                    "7": [
                        5, 
                        6, 
                        7
                    ], 
                    "8": [
                        9, 
                        10, 
                        11
                    ], 
                    "9": [
                        13, 
                        14, 
                        15
                    ], 
                    "10": [
                        17, 
                        18, 
                        16
                    ], 
                    "11": [
                        21, 
                        22, 
                        23
                    ]
                }, 
                "facedata": {
                    "0": {}, 
                    "1": {}, 
                    "2": {}, 
                    "3": {}, 
                    "4": {}, 
                    "5": {}, 
                    "6": {}, 
                    "7": {}, 
                    "8": {}, 
                    "9": {}, 
                    "10": {}, 
                    "11": {}
                }, 
                "max_face": 11, 
                "max_vertex": 23, 
                "vertex": {
                    "0": {
                        "x": 0.15000000596046448, 
                        "y": 1.0, 
                        "z": 0.090000003576278687
                    }, 
                    "1": {
                        "x": 0.15000000596046448, 
                        "y": 1.0, 
                        "z": -0.20999999344348907
                    }, 
                    "2": {
                        "x": 2.0, 
                        "y": 1.0, 
                        "z": 0.090000003576278687
                    }, 
                    "3": {
                        "x": 2.0, 
                        "y": 1.0, 
                        "z": -0.20999999344348907
                    }, 
                    "4": {
                        "x": 2.0, 
                        "y": 1.0, 
                        "z": 0.090000003576278687
                    }, 
                    "5": {
                        "x": 2.0, 
                        "y": 1.0, 
                        "z": -0.20999999344348907
                    }, 
                    "6": {
                        "x": 2.0, 
                        "y": -1.0, 
                        "z": 0.090000003576278687
                    }, 
                    "7": {
                        "x": 2.0, 
                        "y": -1.0, 
                        "z": -0.20999999344348907
                    }, 
                    "8": {
                        "x": 2.0, 
                        "y": -1.0, 
                        "z": 0.090000003576278687
                    }, 
                    "9": {
                        "x": 2.0, 
                        "y": -1.0, 
                        "z": -0.20999999344348907
                    }, 
                    "10": {
                        "x": 0.15000000596046448, 
                        "y": -1.0, 
                        "z": 0.090000003576278687
                    }, 
                    "11": {
                        "x": 0.15000000596046448, 
                        "y": -1.0, 
                        "z": -0.20999999344348907
                    }, 
                    "12": {
                        "x": 0.15000000596046448, 
                        "y": -1.0, 
                        "z": 0.090000003576278687
                    }, 
                    "13": {
                        "x": 0.15000000596046448, 
                        "y": -1.0, 
                        "z": -0.20999999344348907
                    }, 
                    "14": {
                        "x": 0.15000000596046448, 
                        "y": 1.0, 
                        "z": 0.090000003576278687
                    }, 
                    "15": {
                        "x": 0.15000000596046448, 
                        "y": 1.0, 
                        "z": -0.20999999344348907
                    }, 
                    "16": {
                        "x": 0.15000000596046448, 
                        "y": 1.0, 
                        "z": 0.090000003576278687
                    }, 
                    "17": {
                        "x": 0.15000000596046448, 
                        "y": -1.0, 
                        "z": 0.090000003576278687
                    }, 
                    "18": {
                        "x": 2.0, 
                        "y": 1.0, 
                        "z": 0.090000003576278687
                    }, 
                    "19": {
                        "x": 2.0, 
                        "y": -1.0, 
                        "z": 0.090000003576278687
                    }, 
                    "20": {
                        "x": 0.15000000596046448, 
                        "y": 1.0, 
                        "z": -0.20999999344348907
                    }, 
                    "21": {
                        "x": 0.15000000596046448, 
                        "y": -1.0, 
                        "z": -0.20999999344348907
                    }, 
                    "22": {
                        "x": 2.0, 
                        "y": 1.0, 
                        "z": -0.20999999344348907
                    }, 
                    "23": {
                        "x": 2.0, 
                        "y": -1.0, 
                        "z": -0.20999999344348907
                    }
                }
            }
        }, 
        {
            "dtype": "compas.datastructures/Mesh", 
            "guid": "7bf28141-3753-49fc-a2e9-ac1d15541ea5", 
            "value": {
                "attributes": {
                    "name": null
                }, 
                "dea": {}, 
                "dfa": {}, 
                "dva": {
                    "x": 0.0, 
                    "y": 0.0, 
                    "z": 0.0
                }, 
                "edgedata": {}, 
                "face": {
                    "0": [
                        1, 
                        0, 
                        2
                    ], 
                    "1": [
                        5, 
                        4, 
                        6
                    ], 
                    "2": [
                        9, 
                        8, 
                        10
                    ], 
                    "3": [
                        13, 
                        12, 
                        14
                    ], 
                    "4": [
                        17, 
                        19, 
                        18
                    ], 
                    "5": [
                        21, 
                        20, 
                        22
                    ], 
                    "6": [
                        1, 
                        2, 
                        3
                    ], 
                    "7": [
                        5, 
                        6, 
                        7
                    ], 
                    "8": [
                        9, 
                        10, 
                        11
                    ], 
                    "9": [
                        13, 
                        14, 
                        15
                    ], 
                    "10": [
                        17, 
                        18, 
                        16
                    ], 
                    "11": [
                        21, 
                        22, 
                        23
                    ]
                }, 
                "facedata": {
                    "0": {}, 
                    "1": {}, 
                    "2": {}, 
                    "3": {}, 
                    "4": {}, 
                    "5": {}, 
                    "6": {}, 
                    "7": {}, 
                    "8": {}, 
                    "9": {}, 
                    "10": {}, 
                    "11": {}
                }, 
                "max_face": 11, 
                "max_vertex": 23, 
                "vertex": {
                    "0": {
                        "x": -0.20000000298023224, 
                        "y": 0.20000000298023224, 
                        "z": 0.60000002384185791
                    }, 
                    "1": {
                        "x": -0.20000000298023224, 
                        "y": 0.20000000298023224, 
                        "z": 0.0
                    }, 
                    "2": {
                        "x": -0.20000000298023224, 
                        "y": 0.5, 
                        "z": 0.60000002384185791
                    }, 
                    "3": {
                        "x": -0.20000000298023224, 
                        "y": 0.5, 
                        "z": 0.0
                    }, 
                    "4": {
                        "x": -0.20000000298023224, 
                        "y": 0.5, 
                        "z": 0.60000002384185791
                    }, 
                    "5": {
                        "x": -0.20000000298023224, 
                        "y": 0.5, 
                        "z": 0.0
                    }, 
                    "6": {
                        "x": 0.0, 
                        "y": 0.5, 
                        "z": 0.60000002384185791
                    }, 
                    "7": {
                        "x": 0.0, 
                        "y": 0.5, 
                        "z": 0.0
                    }, 
                    "8": {
                        "x": 0.0, 
                        "y": 0.5, 
                        "z": 0.60000002384185791
                    }, 
                    "9": {
                        "x": 0.0, 
                        "y": 0.5, 
                        "z": 0.0
                    }, 
                    "10": {
                        "x": 0.0, 
                        "y": 0.20000000298023224, 
                        "z": 0.60000002384185791
                    }, 
                    "11": {
                        "x": 0.0, 
                        "y": 0.20000000298023224, 
                        "z": 0.0
                    }, 
                    "12": {
                        "x": 0.0, 
                        "y": 0.20000000298023224, 
                        "z": 0.60000002384185791
                    }, 
                    "13": {
                        "x": 0.0, 
                        "y": 0.20000000298023224, 
                        "z": 0.0
                    }, 
                    "14": {
                        "x": -0.20000000298023224, 
                        "y": 0.20000000298023224, 
                        "z": 0.60000002384185791
                    }, 
                    "15": {
                        "x": -0.20000000298023224, 
                        "y": 0.20000000298023224, 
                        "z": 0.0
                    }, 
                    "16": {
                        "x": -0.20000000298023224, 
                        "y": 0.20000000298023224, 
                        "z": 0.60000002384185791
                    }, 
                    "17": {
                        "x": 0.0, 
                        "y": 0.20000000298023224, 
                        "z": 0.60000002384185791
                    }, 
                    "18": {
                        "x": -0.20000000298023224, 
                        "y": 0.5, 
                        "z": 0.60000002384185791
                    }, 
                    "19": {
                        "x": 0.0, 
                        "y": 0.5, 
                        "z": 0.60000002384185791
                    }, 
                    "20": {
                        "x": -0.20000000298023224, 
                        "y": 0.20000000298023224, 
                        "z": 0.0
                    }, 
                    "21": {
                        "x": 0.0, 
                        "y": 0.20000000298023224, 
                        "z": 0.0
                    }, 
                    "22": {
                        "x": -0.20000000298023224, 
                        "y": 0.5, 
                        "z": 0.0
                    }, 
                    "23": {
                        "x": 0.0, 
                        "y": 0.5, 
                        "z": 0.0
                    }
                }
            }
        }, 
        {
            "dtype": "compas.datastructures/Mesh", 
            "guid": "bba3d614-2085-47b8-8323-1fb3191048ce", 
            "value": {
                "attributes": {
                    "name": null
                }, 
                "dea": {}, 
                "dfa": {}, 
                "dva": {
                    "x": 0.0, 
                    "y": 0.0, 
                    "z": 0.0
                }, 
                "edgedata": {}, 
                "face": {
                    "0": [
                        1, 
                        0, 
                        2
                    ], 
                    "1": [
                        5, 
                        4, 
                        6
                    ], 
                    "2": [
                        9, 
                        8, 
                        10
                    ], 
                    "3": [
                        13, 
                        12, 
                        14
                    ], 
                    "4": [
                        17, 
                        19, 
                        18
                    ], 
                    "5": [
                        21, 
                        20, 
                        22
                    ], 
                    "6": [
                        1, 
                        2, 
                        3
                    ], 
                    "7": [
                        5, 
                        6, 
                        7
                    ], 
                    "8": [
                        9, 
                        10, 
                        11
                    ], 
                    "9": [
                        13, 
                        14, 
                        15
                    ], 
                    "10": [
                        17, 
                        18, 
                        16
                    ], 
                    "11": [
                        21, 
                        22, 
                        23
                    ]
                }, 
                "facedata": {
                    "0": {}, 
                    "1": {}, 
                    "2": {}, 
                    "3": {}, 
                    "4": {}, 
                    "5": {}, 
                    "6": {}, 
                    "7": {}, 
                    "8": {}, 
                    "9": {}, 
                    "10": {}, 
                    "11": {}
                }, 
                "max_face": 11, 
                "max_vertex": 23, 
                "vertex": {
                    "0": {
                        "x": -0.5, 
                        "y": -0.30000001192092896, 
                        "z": 0.60000002384185791
                    }, 
                    "1": {
                        "x": -0.5, 
                        "y": -0.30000001192092896, 
                        "z": 0.0
                    }, 
                    "2": {
                        "x": -0.5, 
                        "y": 0.5, 
                        "z": 0.60000002384185791
                    }, 
                    "3": {
                        "x": -0.5, 
                        "y": 0.5, 
                        "z": 0.0
                    }, 
                    "4": {
                        "x": -0.5, 
                        "y": 0.5, 
                        "z": 0.60000002384185791
                    }, 
                    "5": {
                        "x": -0.5, 
                        "y": 0.5, 
                        "z": 0.0
                    }, 
                    "6": {
                        "x": -0.20000000298023224, 
                        "y": 0.5, 
                        "z": 0.60000002384185791
                    }, 
                    "7": {
                        "x": -0.20000000298023224, 
                        "y": 0.5, 
                        "z": 0.0
                    }, 
                    "8": {
                        "x": -0.20000000298023224, 
                        "y": 0.5, 
                        "z": 0.60000002384185791
                    }, 
                    "9": {
                        "x": -0.20000000298023224, 
                        "y": 0.5, 
                        "z": 0.0
                    }, 
                    "10": {
                        "x": -0.20000000298023224, 
                        "y": -0.30000001192092896, 
                        "z": 0.60000002384185791
                    }, 
                    "11": {
                        "x": -0.20000000298023224, 
                        "y": -0.30000001192092896, 
                        "z": 0.0
                    }, 
                    "12": {
                        "x": -0.20000000298023224, 
                        "y": -0.30000001192092896, 
                        "z": 0.60000002384185791
                    }, 
                    "13": {
                        "x": -0.20000000298023224, 
                        "y": -0.30000001192092896, 
                        "z": 0.0
                    }, 
                    "14": {
                        "x": -0.5, 
                        "y": -0.30000001192092896, 
                        "z": 0.60000002384185791
                    }, 
                    "15": {
                        "x": -0.5, 
                        "y": -0.30000001192092896, 
                        "z": 0.0
                    }, 
                    "16": {
                        "x": -0.5, 
                        "y": -0.30000001192092896, 
                        "z": 0.60000002384185791
                    }, 
                    "17": {
                        "x": -0.20000000298023224, 
                        "y": -0.30000001192092896, 
                        "z": 0.60000002384185791
                    }, 
                    "18": {
                        "x": -0.5, 
                        "y": 0.5, 
                        "z": 0.60000002384185791
                    }, 
                    "19": {
                        "x": -0.20000000298023224, 
                        "y": 0.5, 
                        "z": 0.60000002384185791
                    }, 
                    "20": {
                        "x": -0.5, 
                        "y": -0.30000001192092896, 
                        "z": 0.0
                    }, 
                    "21": {
                        "x": -0.20000000298023224, 
                        "y": -0.30000001192092896, 
                        "z": 0.0
                    }, 
                    "22": {
                        "x": -0.5, 
                        "y": 0.5, 
                        "z": 0.0
                    }, 
                    "23": {
                        "x": -0.20000000298023224, 
                        "y": 0.5, 
                        "z": 0.0
                    }
                }
            }
        }, 
        {
            "dtype": "compas.datastructures/Mesh", 
            "guid": "effc79c8-5f21-42f3-a9cd-e4e4510cd73d", 
            "value": {
                "attributes": {
                    "name": null
                }, 
                "dea": {}, 
                "dfa": {}, 
                "dva": {
                    "x": 0.0, 
                    "y": 0.0, 
                    "z": 0.0
                }, 
                "edgedata": {}, 
                "face": {
                    "0": [
                        1, 
                        0, 
                        2
                    ], 
                    "1": [
                        5, 
                        4, 
                        6
                    ], 
                    "2": [
                        9, 
                        8, 
                        10
                    ], 
                    "3": [
                        13, 
                        12, 
                        14
                    ], 
                    "4": [
                        17, 
                        19, 
                        18
                    ], 
                    "5": [
                        21, 
                        20, 
                        22
                    ], 
                    "6": [
                        1, 
                        2, 
                        3
                    ], 
                    "7": [
                        5, 
                        6, 
                        7
                    ], 
                    "8": [
                        9, 
                        10, 
                        11
                    ], 
                    "9": [
                        13, 
                        14, 
                        15
                    ], 
                    "10": [
                        17, 
                        18, 
                        16
                    ], 
                    "11": [
                        21, 
                        22, 
                        23
                    ]
                }, 
                "facedata": {
                    "0": {}, 
                    "1": {}, 
                    "2": {}, 
                    "3": {}, 
                    "4": {}, 
                    "5": {}, 
                    "6": {}, 
                    "7": {}, 
                    "8": {}, 
                    "9": {}, 
                    "10": {}, 
                    "11": {}
                }, 
                "max_face": 11, 
                "max_vertex": 23, 
                "vertex": {
                    "0": {
                        "x": -1.0, 
                        "y": 1.0, 
                        "z": -0.0099999997764825821
                    }, 
                    "1": {
                        "x": -1.0, 
                        "y": 1.0, 
                        "z": -0.20999999344348907
                    }, 
                    "2": {
                        "x": 0.15000000596046448, 
                        "y": 1.0, 
                        "z": -0.0099999997764825821
                    }, 
                    "3": {
                        "x": 0.15000000596046448, 
                        "y": 1.0, 
                        "z": -0.20999999344348907
                    }, 
                    "4": {
                        "x": 0.15000000596046448, 
                        "y": 1.0, 
                        "z": -0.0099999997764825821
                    }, 
                    "5": {
                        "x": 0.15000000596046448, 
                        "y": 1.0, 
                        "z": -0.20999999344348907
                    }, 
                    "6": {
                        "x": 0.15000000596046448, 
                        "y": -1.0, 
                        "z": -0.0099999997764825821
                    }, 
                    "7": {
                        "x": 0.15000000596046448, 
                        "y": -1.0, 
                        "z": -0.20999999344348907
                    }, 
                    "8": {
                        "x": 0.15000000596046448, 
                        "y": -1.0, 
                        "z": -0.0099999997764825821
                    }, 
                    "9": {
                        "x": 0.15000000596046448, 
                        "y": -1.0, 
                        "z": -0.20999999344348907
                    }, 
                    "10": {
                        "x": -1.0, 
                        "y": -1.0, 
                        "z": -0.0099999997764825821
                    }, 
                    "11": {
                        "x": -1.0, 
                        "y": -1.0, 
                        "z": -0.20999999344348907
                    }, 
                    "12": {
                        "x": -1.0, 
                        "y": -1.0, 
                        "z": -0.0099999997764825821
                    }, 
                    "13": {
                        "x": -1.0, 
                        "y": -1.0, 
                        "z": -0.20999999344348907
                    }, 
                    "14": {
                        "x": -1.0, 
                        "y": 1.0, 
                        "z": -0.0099999997764825821
                    }, 
                    "15": {
                        "x": -1.0, 
                        "y": 1.0, 
                        "z": -0.20999999344348907
                    }, 
                    "16": {
                        "x": -1.0, 
                        "y": 1.0, 
                        "z": -0.0099999997764825821
                    }, 
                    "17": {
                        "x": -1.0, 
                        "y": -1.0, 
                        "z": -0.0099999997764825821
                    }, 
                    "18": {
                        "x": 0.15000000596046448, 
                        "y": 1.0, 
                        "z": -0.0099999997764825821
                    }, 
                    "19": {
                        "x": 0.15000000596046448, 
                        "y": -1.0, 
                        "z": -0.0099999997764825821
                    }, 
                    "20": {
                        "x": -1.0, 
                        "y": 1.0, 
                        "z": -0.20999999344348907
                    }, 
                    "21": {
                        "x": -1.0, 
                        "y": -1.0, 
                        "z": -0.20999999344348907
                    }, 
                    "22": {
                        "x": 0.15000000596046448, 
                        "y": 1.0, 
                        "z": -0.20999999344348907
                    }, 
                    "23": {
                        "x": 0.15000000596046448, 
                        "y": -1.0, 
                        "z": -0.20999999344348907
                    }
                }
            }
        }, 
        {
            "dtype": "compas.datastructures/Mesh", 
            "guid": "2fb44bda-dab2-4ecf-a7df-9f119fd0739f", 
            "value": {
                "attributes": {
                    "name": null
                }, 
                "dea": {}, 
                "dfa": {}, 
                "dva": {
                    "x": 0.0, 
                    "y": 0.0, 
                    "z": 0.0
                }, 
                "edgedata": {}, 
                "face": {
                    "0": [
                        1, 
                        0, 
                        2
                    ], 
                    "1": [
                        5, 
                        4, 
                        6
                    ], 
                    "2": [
                        9, 
                        8, 
                        10
                    ], 
                    "3": [
                        13, 
                        12, 
                        14
                    ], 
                    "4": [
                        17, 
                        19, 
                        18
                    ], 
                    "5": [
                        21, 
                        20, 
                        22
                    ], 
                    "6": [
                        1, 
                        2, 
                        3
                    ], 
                    "7": [
                        5, 
                        6, 
                        7
                    ], 
                    "8": [
                        9, 
                        10, 
                        11
                    ], 
                    "9": [
                        13, 
                        14, 
                        15
                    ], 
                    "10": [
                        17, 
                        18, 
                        16
                    ], 
                    "11": [
                        21, 
                        22, 
                        23
                    ]
                }, 
                "facedata": {
                    "0": {}, 
                    "1": {}, 
                    "2": {}, 
                    "3": {}, 
                    "4": {}, 
                    "5": {}, 
                    "6": {}, 
                    "7": {}, 
                    "8": {}, 
                    "9": {}, 
                    "10": {}, 
                    "11": {}
                }, 
                "max_face": 11, 
                "max_vertex": 23, 
                "vertex": {
                    "0": {
                        "x": 0.40542164444923401, 
                        "y": -0.38777488470077515, 
                        "z": -0.28502970933914185
                    }, 
                    "1": {
                        "x": 0.40542164444923401, 
                        "y": -0.38777488470077515, 
                        "z": 1.0223325490951538
                    }, 
                    "2": {
                        "x": 0.6980971097946167, 
                        "y": -0.38777488470077515, 
                        "z": -0.28502970933914185
                    }, 
                    "3": {
                        "x": 0.6980971097946167, 
                        "y": -0.38777488470077515, 
                        "z": 1.0223325490951538
                    }, 
                    "4": {
                        "x": 0.6980971097946167, 
                        "y": -0.38777488470077515, 
                        "z": -0.28502970933914185
                    }, 
                    "5": {
                        "x": 0.6980971097946167, 
                        "y": -0.38777488470077515, 
                        "z": 1.0223325490951538
                    }, 
                    "6": {
                        "x": 0.6980971097946167, 
                        "y": -0.21358112990856171, 
                        "z": -0.28502970933914185
                    }, 
                    "7": {
                        "x": 0.6980971097946167, 
                        "y": -0.21358112990856171, 
                        "z": 1.0223325490951538
                    }, 
                    "8": {
                        "x": 0.6980971097946167, 
                        "y": -0.21358112990856171, 
                        "z": -0.28502970933914185
                    }, 
                    "9": {
                        "x": 0.6980971097946167, 
                        "y": -0.21358112990856171, 
                        "z": 1.0223325490951538
                    }, 
                    "10": {
                        "x": 0.40542164444923401, 
                        "y": -0.21358112990856171, 
                        "z": -0.28502970933914185
                    }, 
                    "11": {
                        "x": 0.40542164444923401, 
                        "y": -0.21358112990856171, 
                        "z": 1.0223325490951538
                    }, 
                    "12": {
                        "x": 0.40542164444923401, 
                        "y": -0.21358112990856171, 
                        "z": -0.28502970933914185
                    }, 
                    "13": {
                        "x": 0.40542164444923401, 
                        "y": -0.21358112990856171, 
                        "z": 1.0223325490951538
                    }, 
                    "14": {
                        "x": 0.40542164444923401, 
                        "y": -0.38777488470077515, 
                        "z": -0.28502970933914185
                    }, 
                    "15": {
                        "x": 0.40542164444923401, 
                        "y": -0.38777488470077515, 
                        "z": 1.0223325490951538
                    }, 
                    "16": {
                        "x": 0.40542164444923401, 
                        "y": -0.38777488470077515, 
                        "z": -0.28502970933914185
                    }, 
                    "17": {
                        "x": 0.40542164444923401, 
                        "y": -0.21358112990856171, 
                        "z": -0.28502970933914185
                    }, 
                    "18": {
                        "x": 0.6980971097946167, 
                        "y": -0.38777488470077515, 
                        "z": -0.28502970933914185
                    }, 
                    "19": {
                        "x": 0.6980971097946167, 
                        "y": -0.21358112990856171, 
                        "z": -0.28502970933914185
                    }, 
                    "20": {
                        "x": 0.40542164444923401, 
                        "y": -0.38777488470077515, 
                        "z": 1.0223325490951538
                    }, 
                    "21": {
                        "x": 0.40542164444923401, 
                        "y": -0.21358112990856171, 
                        "z": 1.0223325490951538
                    }, 
                    "22": {
                        "x": 0.6980971097946167, 
                        "y": -0.38777488470077515, 
                        "z": 1.0223325490951538
                    }, 
                    "23": {
                        "x": 0.6980971097946167, 
                        "y": -0.21358112990856171, 
                        "z": 1.0223325490951538
                    }
                }
            }
        }
    ], 
    "end_configuration": null, 
    "start_configuration": null
}